[
    {
      "id": 1,
      "name": "Mark De Guzman",
      "purpose": "Enrollment",
      "status": "Completed"
    },
    {
      "id": 2,
      "name": "Bulkang Taal",
      "purpose": "Enrollment",
      "status": "Completed"
    },
    {
      "id": 3,
      "name": "Jeds Island Resort",
      "purpose": "Examination",
      "status": "Completed"
    },
    {
      "id": 4,
      "name": "Mr Long Bomb",
      "purpose": "Balance",
      "status": "Cancelled"
    },
    {
      "id": 5,
      "name": "Mcarthur Highway",
      "purpose": "Balance, Examination",
      "status": "Completed"
    },
    {
      "id": 6,
      "name": "Tanduay Rhum",
      "purpose": "Enrollment, Examination, Balance",
      "status": "Cancelled"
    },
    {
      "id": 7,
      "name": "Ronel Balingit",
      "purpose": "Enrollment",
      "status": "Completed"
    }
  ]
  